tcpChat/__init__.py
tcpChat/tcpchat.py
clevrthings_tcpChat-0.1.5.dist-info/LICENSE
clevrthings_tcpChat-0.1.5.dist-info/METADATA
clevrthings_tcpChat-0.1.5.dist-info/WHEEL
clevrthings_tcpChat-0.1.5.dist-info/top_level.txt
clevrthings_tcpChat-0.1.5.dist-info/RECORD
