Metadata-Version: 2.1
Name: clevrthings-tcpChat
Version: 0.1.5
Summary: A simple Python module for creating a TCP chat connection between two computers to send commands or information.
Home-page: https://github.com/clevrthings/tcpChat
Author: Clevrthings
Author-email: info@clevrthings.com
Classifier: Programming Language :: Python :: 3
Classifier: License :: OSI Approved :: MIT License
Classifier: Operating System :: OS Independent
Requires-Python: >=3.6
License-File: LICENSE
